
[{
	"name": "home",
	"path": "./icons/svg/home.svg",
	"tags": ["home","house"]
},
{
	"name": "edit",
	"path": "./icons/svg/edit.svg",
	"tags": ["edit","modify"]
},
{
	"name": "search",
	"path": "./icons/svg/search.svg",
	"tags": ["search","find","magnify"]
},
{
	"name": "settings",
	"path": "./icons/svg/settings.svg",
	"tags": ["settings","gear","preferences"]
},
{
	"name": "user",
	"path": "./icons/svg/user.svg",
	"tags": ["user","person","account"]
}, 
{
	"name": "cart",
	"path": "./icons/svg/cart.svg",
	"tags": ["cart","shopping","basket"]
},
{
	"name": "library",
	"path": "./icons/svg/library.svg",
	"tags": ["library","books","collection"]
}
]
